MANIFEST.in
README.txt
requirements.txt
setup.py
test_requirements.txt
version.txt
cloudshell/__init__.py
cloudshell/firewall/__init__.py
cloudshell/firewall/juniper/__init__.py
cloudshell/firewall/juniper/junos/__init__.py
cloudshell/firewall/juniper/junos/utils.py
cloudshell/firewall/juniper/junos/autoload/__init__.py
cloudshell/firewall/juniper/junos/autoload/juniper_snmp_autoload.py
cloudshell/firewall/juniper/junos/cli/__init__.py
cloudshell/firewall/juniper/junos/cli/juniper_cli_handler.py
cloudshell/firewall/juniper/junos/cli/juniper_command_modes.py
cloudshell/firewall/juniper/junos/command_actions/__init__.py
cloudshell/firewall/juniper/junos/command_actions/commit_rollback_actions.py
cloudshell/firewall/juniper/junos/command_actions/enable_disable_snmp_actions.py
cloudshell/firewall/juniper/junos/command_actions/save_restore_actions.py
cloudshell/firewall/juniper/junos/command_actions/system_actions.py
cloudshell/firewall/juniper/junos/command_templates/__init__.py
cloudshell/firewall/juniper/junos/command_templates/commit_rollback.py
cloudshell/firewall/juniper/junos/command_templates/enable_disable_snmp.py
cloudshell/firewall/juniper/junos/command_templates/save_restore.py
cloudshell/firewall/juniper/junos/command_templates/system_commands.py
cloudshell/firewall/juniper/junos/flows/__init__.py
cloudshell/firewall/juniper/junos/flows/juniper_autoload_flow.py
cloudshell/firewall/juniper/junos/flows/juniper_disable_snmp_flow.py
cloudshell/firewall/juniper/junos/flows/juniper_enable_snmp_flow.py
cloudshell/firewall/juniper/junos/flows/juniper_firmware_flow.py
cloudshell/firewall/juniper/junos/flows/juniper_restore_flow.py
cloudshell/firewall/juniper/junos/flows/juniper_save_flow.py
cloudshell/firewall/juniper/junos/flows/juniper_shutdown_flow.py
cloudshell/firewall/juniper/junos/helpers/__init__.py
cloudshell/firewall/juniper/junos/helpers/save_restore_helper.py
cloudshell/firewall/juniper/junos/mibs/JUNIPER-CHASSIS-DEFINES-MIB.py
cloudshell_firewall_juniper_junos.egg-info/PKG-INFO
cloudshell_firewall_juniper_junos.egg-info/SOURCES.txt
cloudshell_firewall_juniper_junos.egg-info/dependency_links.txt
cloudshell_firewall_juniper_junos.egg-info/requires.txt
cloudshell_firewall_juniper_junos.egg-info/top_level.txt