Metadata-Version: 1.0
Name: cloudshell-firewall-juniper-junos
Version: 1.0.3
Summary: QualiSystems firewall Juniper JunOS specific Package
Home-page: http://www.qualisystems.com/
Author: QualiSystems
Author-email: info@qualisystems.com
License: UNKNOWN
Platform: UNKNOWN
